sorunlib/__init__.py
sorunlib/_internal.py
sorunlib/_version.py
sorunlib/acu.py
sorunlib/commands.py
sorunlib/config.py
sorunlib/hwp.py
sorunlib/seq.py
sorunlib/smurf.py
sorunlib/stimulator.py
sorunlib/util.py
sorunlib/wiregrid.py
sorunlib-0.1.31.dist-info/METADATA
sorunlib-0.1.31.dist-info/WHEEL
sorunlib-0.1.31.dist-info/licenses/LICENSE.txt
sorunlib-0.1.31.dist-info/RECORD
