Metadata-Version: 2.4
Name: sorunlib
Version: 0.1.31
Summary: OCS Control Programs for running the observatory.
Project-URL: Bug Tracker, https://github.com/simonsobs/sorunlib/issues
Project-URL: Documentation, https://sorunlib.readthedocs.io
Project-URL: Homepage, https://github.com/simonsobs/sorunlib
Project-URL: Source Code, https://github.com/simonsobs/sorunlib
License-Expression: BSD-2-Clause
License-File: LICENSE.txt
Classifier: Intended Audience :: Science/Research
Classifier: Programming Language :: Python :: 3
Classifier: Programming Language :: Python :: 3 :: Only
Classifier: Programming Language :: Python :: 3.9
Classifier: Programming Language :: Python :: 3.10
Classifier: Programming Language :: Python :: 3.11
Classifier: Programming Language :: Python :: 3.12
Classifier: Topic :: Scientific/Engineering :: Astronomy
Requires-Python: >=3.9
Requires-Dist: ocs==0.11.3
Requires-Dist: pyyaml
Provides-Extra: dev
Requires-Dist: pytest-cov>=3.0.0; extra == 'dev'
Requires-Dist: pytest-mock>=3.12.0; extra == 'dev'
Requires-Dist: pytest>=7.0.0; extra == 'dev'
Requires-Dist: setuptools-scm; extra == 'dev'
Provides-Extra: docs
Requires-Dist: sphinx-rtd-theme>=1.1.1; extra == 'docs'
Requires-Dist: sphinx>=5.3.0; extra == 'docs'
